drq/__init__.py
drq/core.py
drq-0.0.1.dist-info/licenses/LICENSE
drq-0.0.1.dist-info/METADATA
drq-0.0.1.dist-info/WHEEL
drq-0.0.1.dist-info/top_level.txt
drq-0.0.1.dist-info/RECORD
