Metadata-Version: 2.4
Name: drq
Version: 0.0.1
Summary: A constantly updated small project, which contains some entertainment and practical functions, such as random words and so on.
Author-email: Init_V2 <searchstars@qq.com>
License: MIT
Project-URL: Homepage, https://github.com/InitV2/drq
Requires-Python: >=3.8
License-File: LICENSE
Requires-Dist: requests>=2.31
Dynamic: license-file
